{
  "info": {
    "_postman_id": "b1e1e1e1-1111-2222-3333-444444444444",
    "name": "Kontext API Collection",
    "description": "Complete API collection for Kontext RAG-based document processing platform",
    "schema": "https://schema.getpostman.com/json/collection/v2.1.0/collection.json",
    "_exporter_id": "12345"
  },
  "item": [
    {
      "name": "Authentication",
      "item": [
        {
          "name": "Register User",
          "request": {
            "method": "POST",
            "header": [
              {
                "key": "Content-Type",
                "value": "application/json"
              }
            ],
            "body": {
              "mode": "raw",
              "raw": "{\n  \"username\": \"john_doe\",\n  \"email\": \"john.doe@example.com\",\n  \"fullName\": \"John Doe\",\n  \"password\": \"password123\"\n}"
            },
            "url": {
              "raw": "{{base_url}}/api/v1/auth/register",
              "host": ["{{base_url}}"],
              "path": ["api", "v1", "auth", "register"]
            }
          }
        },
        {
          "name": "Login",
          "request": {
            "method": "POST",
            "header": [
              {
                "key": "Content-Type",
                "value": "application/json"
              }
            ],
            "body": {
              "mode": "raw",
              "raw": "{\n  \"username\": \"john_doe\",\n  \"password\": \"password123\"\n}"
            },
            "url": {
              "raw": "{{base_url}}/api/v1/auth/login",
              "host": ["{{base_url}}"],
              "path": ["api", "v1", "auth", "login"]
            }
          }
        },
        {
          "name": "Get Current User",
          "request": {
            "method": "GET",
            "header": [
              {
                "key": "Authorization",
                "value": "Bearer {{jwt_token}}"
              }
            ],
            "url": {
              "raw": "{{base_url}}/api/v1/auth/me",
              "host": ["{{base_url}}"],
              "path": ["api", "v1", "auth", "me"]
            }
          }
        }
      ]
    },
    {
      "name": "Health Check",
      "item": [
        {
          "name": "Health Status",
          "request": {
            "method": "GET",
            "header": [],
            "url": {
              "raw": "{{base_url}}/health",
              "host": ["{{base_url}}"],
              "path": ["health"]
            }
          }
        },
        {
          "name": "Health Ping",
          "request": {
            "method": "GET",
            "header": [],
            "url": {
              "raw": "{{base_url}}/health/ping",
              "host": ["{{base_url}}"],
              "path": ["health", "ping"]
            }
          }
        }
      ]
    },
    {
      "name": "User Management",
      "item": [
        {
          "name": "Create User",
          "request": {
            "method": "POST",
            "header": [
              {
                "key": "Content-Type",
                "value": "application/json"
              },
              {
                "key": "Authorization",
                "value": "Bearer {{jwt_token}}"
              }
            ],
            "body": {
              "mode": "raw",
              "raw": "{\n  \"username\": \"john_doe\",\n  \"email\": \"john.doe@example.com\",\n  \"fullName\": \"John Doe\"\n}"
            },
            "url": {
              "raw": "{{base_url}}/api/v1/users",
              "host": ["{{base_url}}"],
              "path": ["api", "v1", "users"]
            }
          }
        },
        {
          "name": "Get User by ID",
          "request": {
            "method": "GET",
            "header": [],
            "url": {
              "raw": "{{base_url}}/api/v1/users/{{user_id}}",
              "host": ["{{base_url}}"],
              "path": ["api", "v1", "users", "{{user_id}}"]
            }
          }
        },
        {
          "name": "Get User by Username",
          "request": {
            "method": "GET",
            "header": [],
            "url": {
              "raw": "{{base_url}}/api/v1/users/username/{{username}}",
              "host": ["{{base_url}}"],
              "path": ["api", "v1", "users", "username", "{{username}}"]
            }
          }
        },
        {
          "name": "List Users",
          "request": {
            "method": "GET",
            "header": [],
            "url": {
              "raw": "{{base_url}}/api/v1/users?page=0&size=10&sortBy=id&sortDir=asc&search=",
              "host": ["{{base_url}}"],
              "path": ["api", "v1", "users"],
              "query": [
                {"key": "page", "value": "0"},
                {"key": "size", "value": "10"},
                {"key": "sortBy", "value": "id"},
                {"key": "sortDir", "value": "asc"},
                {"key": "search", "value": ""}
              ]
            }
          }
        },
        {
          "name": "Update User",
          "request": {
            "method": "PUT",
            "header": [
              {
                "key": "Content-Type",
                "value": "application/json"
              }
            ],
            "body": {
              "mode": "raw",
              "raw": "{\n  \"username\": \"john_doe_updated\",\n  \"email\": \"john.updated@example.com\",\n  \"fullName\": \"John Doe Updated\",\n  \"status\": \"ACTIVE\"\n}"
            },
            "url": {
              "raw": "{{base_url}}/api/v1/users/{{user_id}}",
              "host": ["{{base_url}}"],
              "path": ["api", "v1", "users", "{{user_id}}"]
            }
          }
        },
        {
          "name": "Delete User",
          "request": {
            "method": "DELETE",
            "header": [],
            "url": {
              "raw": "{{base_url}}/api/v1/users/{{user_id}}",
              "host": ["{{base_url}}"],
              "path": ["api", "v1", "users", "{{user_id}}"]
            }
          }
        }
      ]
    },
    {
      "name": "Project Management",
      "item": [
        {
          "name": "Create Project",
          "request": {
            "method": "POST",
            "header": [
              {
                "key": "Content-Type",
                "value": "application/json"
              },
              {
                "key": "X-User-Id",
                "value": "{{user_id}}"
              }
            ],
            "body": {
              "mode": "raw",
              "raw": "{\n  \"name\": \"AI Research Project\",\n  \"description\": \"Project for processing AI research papers\",\n  \"type\": \"DOCUMENT_BASED\"\n}"
            },
            "url": {
              "raw": "{{base_url}}/api/v1/projects",
              "host": ["{{base_url}}"],
              "path": ["api", "v1", "projects"]
            }
          }
        },
        {
          "name": "Get Project by ID",
          "request": {
            "method": "GET",
            "header": [
              {
                "key": "X-User-Id",
                "value": "{{user_id}}"
              }
            ],
            "url": {
              "raw": "{{base_url}}/api/v1/projects/{{project_id}}",
              "host": ["{{base_url}}"],
              "path": ["api", "v1", "projects", "{{project_id}}"]
            }
          }
        },
        {
          "name": "List User Projects",
          "request": {
            "method": "GET",
            "header": [
              {
                "key": "X-User-Id",
                "value": "{{user_id}}"
              }
            ],
            "url": {
              "raw": "{{base_url}}/api/v1/projects?page=0&size=20",
              "host": ["{{base_url}}"],
              "path": ["api", "v1", "projects"],
              "query": [
                {"key": "page", "value": "0"},
                {"key": "size", "value": "20"}
              ]
            }
          }
        },
        {
          "name": "Search Projects",
          "request": {
            "method": "GET",
            "header": [
              {
                "key": "X-User-Id",
                "value": "{{user_id}}"
              }
            ],
            "url": {
              "raw": "{{base_url}}/api/v1/projects/search?q=research&page=0&size=20",
              "host": ["{{base_url}}"],
              "path": ["api", "v1", "projects", "search"],
              "query": [
                {"key": "q", "value": "research"},
                {"key": "page", "value": "0"},
                {"key": "size", "value": "20"}
              ]
            }
          }
        },
        {
          "name": "Update Project",
          "request": {
            "method": "PUT",
            "header": [
              {
                "key": "Content-Type",
                "value": "application/json"
              },
              {
                "key": "X-User-Id",
                "value": "{{user_id}}"
              }
            ],
            "body": {
              "mode": "raw",
              "raw": "{\n  \"name\": \"Updated AI Research Project\",\n  \"description\": \"Updated project description\",\n  \"status\": \"ACTIVE\"\n}"
            },
            "url": {
              "raw": "{{base_url}}/api/v1/projects/{{project_id}}",
              "host": ["{{base_url}}"],
              "path": ["api", "v1", "projects", "{{project_id}}"]
            }
          }
        },
        {
          "name": "Update Processing Status",
          "request": {
            "method": "PUT",
            "header": [
              {
                "key": "X-User-Id",
                "value": "{{user_id}}"
              }
            ],
            "url": {
              "raw": "{{base_url}}/api/v1/projects/{{project_id}}/processing-status?status=PROCESSING",
              "host": ["{{base_url}}"],
              "path": ["api", "v1", "projects", "{{project_id}}", "processing-status"],
              "query": [
                {"key": "status", "value": "PROCESSING"}
              ]
            }
          }
        },
        {
          "name": "Delete Project",
          "request": {
            "method": "DELETE",
            "header": [
              {
                "key": "X-User-Id",
                "value": "{{user_id}}"
              }
            ],
            "url": {
              "raw": "{{base_url}}/api/v1/projects/{{project_id}}",
              "host": ["{{base_url}}"],
              "path": ["api", "v1", "projects", "{{project_id}}"]
            }
          }
        }
      ]
    },
    {
      "name": "Document Management",
      "item": [
        {
          "name": "Upload Document",
          "request": {
            "method": "POST",
            "header": [
              {
                "key": "X-User-Id",
                "value": "{{user_id}}"
              }
            ],
            "body": {
              "mode": "formdata",
              "formdata": [
                {
                  "key": "file",
                  "type": "file",
                  "src": ""
                },
                {
                  "key": "projectId",
                  "value": "{{project_id}}",
                  "type": "text"
                }
              ]
            },
            "url": {
              "raw": "{{base_url}}/api/v1/documents/upload",
              "host": ["{{base_url}}"],
              "path": ["api", "v1", "documents", "upload"]
            }
          }
        },
        {
          "name": "Get Document by ID",
          "request": {
            "method": "GET",
            "header": [
              {
                "key": "X-User-Id",
                "value": "{{user_id}}"
              }
            ],
            "url": {
              "raw": "{{base_url}}/api/v1/documents/{{document_id}}",
              "host": ["{{base_url}}"],
              "path": ["api", "v1", "documents", "{{document_id}}"]
            }
          }
        },
        {
          "name": "List Project Documents",
          "request": {
            "method": "GET",
            "header": [
              {
                "key": "X-User-Id",
                "value": "{{user_id}}"
              }
            ],
            "url": {
              "raw": "{{base_url}}/api/v1/documents/project/{{project_id}}?page=0&size=20",
              "host": ["{{base_url}}"],
              "path": ["api", "v1", "documents", "project", "{{project_id}}"],
              "query": [
                {"key": "page", "value": "0"},
                {"key": "size", "value": "20"}
              ]
            }
          }
        },
        {
          "name": "Search Documents",
          "request": {
            "method": "GET",
            "header": [
              {
                "key": "X-User-Id",
                "value": "{{user_id}}"
              }
            ],
            "url": {
              "raw": "{{base_url}}/api/v1/documents/project/{{project_id}}/search?q=report&page=0&size=20",
              "host": ["{{base_url}}"],
              "path": ["api", "v1", "documents", "project", "{{project_id}}", "search"],
              "query": [
                {"key": "q", "value": "report"},
                {"key": "page", "value": "0"},
                {"key": "size", "value": "20"}
              ]
            }
          }
        },
        {
          "name": "Get Documents by Status",
          "request": {
            "method": "GET",
            "header": [
              {
                "key": "X-User-Id",
                "value": "{{user_id}}"
              }
            ],
            "url": {
              "raw": "{{base_url}}/api/v1/documents/project/{{project_id}}/by-status?status=PROCESSED",
              "host": ["{{base_url}}"],
              "path": ["api", "v1", "documents", "project", "{{project_id}}", "by-status"],
              "query": [
                {"key": "status", "value": "PROCESSED"}
              ]
            }
          }
        },
        {
          "name": "Update Processing Status",
          "request": {
            "method": "PUT",
            "header": [],
            "url": {
              "raw": "{{base_url}}/api/v1/documents/{{document_id}}/processing-status?status=PROCESSING&progress=50",
              "host": ["{{base_url}}"],
              "path": ["api", "v1", "documents", "{{document_id}}", "processing-status"],
              "query": [
                {"key": "status", "value": "PROCESSING"},
                {"key": "progress", "value": "50"}
              ]
            }
          }
        },
        {
          "name": "Delete Document",
          "request": {
            "method": "DELETE",
            "header": [
              {
                "key": "X-User-Id",
                "value": "{{user_id}}"
              }
            ],
            "url": {
              "raw": "{{base_url}}/api/v1/documents/{{document_id}}",
              "host": ["{{base_url}}"],
              "path": ["api", "v1", "documents", "{{document_id}}"]
            }
          }
        }
      ]
    },
    {
      "name": "Processing Jobs",
      "item": [
        {
          "name": "Create Processing Job",
          "request": {
            "method": "POST",
            "header": [
              {
                "key": "Content-Type",
                "value": "application/json"
              }
            ],
            "body": {
              "mode": "raw",
              "raw": "{\n  \"projectId\": {{project_id}},\n  \"documentId\": {{document_id}},\n  \"jobType\": \"DOCUMENT_PROCESSING\",\n  \"processingParameters\": \"{\\\"chunkSize\\\": \\\"1000\\\", \\\"chunkOverlap\\\": \\\"200\\\"}\"\n}"
            },
            "url": {
              "raw": "{{base_url}}/api/v1/processing-jobs",
              "host": ["{{base_url}}"],
              "path": ["api", "v1", "processing-jobs"]
            }
          }
        },
        {
          "name": "Get Job by ID",
          "request": {
            "method": "GET",
            "header": [],
            "url": {
              "raw": "{{base_url}}/api/v1/processing-jobs/{{job_id}}",
              "host": ["{{base_url}}"],
              "path": ["api", "v1", "processing-jobs", "{{job_id}}"]
            }
          }
        },
        {
          "name": "List Project Jobs",
          "request": {
            "method": "GET",
            "header": [
              {
                "key": "X-User-Id",
                "value": "{{user_id}}"
              }
            ],
            "url": {
              "raw": "{{base_url}}/api/v1/processing-jobs/project/{{project_id}}?page=0&size=20",
              "host": ["{{base_url}}"],
              "path": ["api", "v1", "processing-jobs", "project", "{{project_id}}"],
              "query": [
                {"key": "page", "value": "0"},
                {"key": "size", "value": "20"}
              ]
            }
          }
        },
        {
          "name": "Update Job Status",
          "request": {
            "method": "PUT",
            "header": [],
            "url": {
              "raw": "{{base_url}}/api/v1/processing-jobs/{{job_id}}/status?status=PROCESSING&progress=75",
              "host": ["{{base_url}}"],
              "path": ["api", "v1", "processing-jobs", "{{job_id}}", "status"],
              "query": [
                {"key": "status", "value": "PROCESSING"},
                {"key": "progress", "value": "75"}
              ]
            }
          }
        },
        {
          "name": "Retry Job",
          "request": {
            "method": "PUT",
            "header": [],
            "url": {
              "raw": "{{base_url}}/api/v1/processing-jobs/{{job_id}}/retry",
              "host": ["{{base_url}}"],
              "path": ["api", "v1", "processing-jobs", "{{job_id}}", "retry"]
            }
          }
        },
        {
          "name": "Cancel Job",
          "request": {
            "method": "PUT",
            "header": [],
            "url": {
              "raw": "{{base_url}}/api/v1/processing-jobs/{{job_id}}/cancel",
              "host": ["{{base_url}}"],
              "path": ["api", "v1", "processing-jobs", "{{job_id}}", "cancel"]
            }
          }
        }
      ]
    },
    {
      "name": "Knowledge Management",
      "item": [
        {
          "name": "Create Knowledge Chunk",
          "request": {
            "method": "POST",
            "header": [
              {
                "key": "Content-Type",
                "value": "application/json"
              },
              {
                "key": "X-User-Id",
                "value": "{{user_id}}"
              }
            ],
            "body": {
              "mode": "raw",
              "raw": "{\n  \"projectId\": {{project_id}},\n  \"documentId\": {{document_id}},\n  \"content\": \"This is a sample knowledge chunk content extracted from the document.\",\n  \"chunkIndex\": 1,\n  \"chunkSize\": 150,\n  \"chunkType\": \"TEXT\",\n  \"title\": \"Introduction\",\n  \"summary\": \"Brief introduction to the topic\"\n}"
            },
            "url": {
              "raw": "{{base_url}}/api/v1/knowledge",
              "host": ["{{base_url}}"],
              "path": ["api", "v1", "knowledge"]
            }
          }
        },
        {
          "name": "Create Knowledge Batch",
          "request": {
            "method": "POST",
            "header": [
              {
                "key": "Content-Type",
                "value": "application/json"
              },
              {
                "key": "X-User-Id",
                "value": "{{user_id}}"
              }
            ],
            "body": {
              "mode": "raw",
              "raw": "[\n  {\n    \"projectId\": {{project_id}},\n    \"documentId\": {{document_id}},\n    \"content\": \"First knowledge chunk\",\n    \"chunkIndex\": 1,\n    \"chunkType\": \"TEXT\"\n  },\n  {\n    \"projectId\": {{project_id}},\n    \"documentId\": {{document_id}},\n    \"content\": \"Second knowledge chunk\",\n    \"chunkIndex\": 2,\n    \"chunkType\": \"TEXT\"\n  }\n]"
            },
            "url": {
              "raw": "{{base_url}}/api/v1/knowledge/batch",
              "host": ["{{base_url}}"],
              "path": ["api", "v1", "knowledge", "batch"]
            }
          }
        },
        {
          "name": "Get Knowledge by ID",
          "request": {
            "method": "GET",
            "header": [
              {
                "key": "X-User-Id",
                "value": "{{user_id}}"
              }
            ],
            "url": {
              "raw": "{{base_url}}/api/v1/knowledge/{{knowledge_id}}",
              "host": ["{{base_url}}"],
              "path": ["api", "v1", "knowledge", "{{knowledge_id}}"]
            }
          }
        },
        {
          "name": "List Project Knowledge",
          "request": {
            "method": "GET",
            "header": [
              {
                "key": "X-User-Id",
                "value": "{{user_id}}"
              }
            ],
            "url": {
              "raw": "{{base_url}}/api/v1/knowledge/project/{{project_id}}?page=0&size=20",
              "host": ["{{base_url}}"],
              "path": ["api", "v1", "knowledge", "project", "{{project_id}}"],
              "query": [
                {"key": "page", "value": "0"},
                {"key": "size", "value": "20"}
              ]
            }
          }
        },
        {
          "name": "Search Knowledge",
          "request": {
            "method": "GET",
            "header": [
              {
                "key": "X-User-Id",
                "value": "{{user_id}}"
              }
            ],
            "url": {
              "raw": "{{base_url}}/api/v1/knowledge/project/{{project_id}}/search?q=introduction&page=0&size=20",
              "host": ["{{base_url}}"],
              "path": ["api", "v1", "knowledge", "project", "{{project_id}}", "search"],
              "query": [
                {"key": "q", "value": "introduction"},
                {"key": "page", "value": "0"},
                {"key": "size", "value": "20"}
              ]
            }
          }
        },
        {
          "name": "Get Knowledge by Type",
          "request": {
            "method": "GET",
            "header": [
              {
                "key": "X-User-Id",
                "value": "{{user_id}}"
              }
            ],
            "url": {
              "raw": "{{base_url}}/api/v1/knowledge/project/{{project_id}}/by-type?chunkType=TEXT&page=0&size=20",
              "host": ["{{base_url}}"],
              "path": ["api", "v1", "knowledge", "project", "{{project_id}}", "by-type"],
              "query": [
                {"key": "chunkType", "value": "TEXT"},
                {"key": "page", "value": "0"},
                {"key": "size", "value": "20"}
              ]
            }
          }
        },
        {
          "name": "Update Knowledge Embeddings",
          "request": {
            "method": "PUT",
            "header": [],
            "url": {
              "raw": "{{base_url}}/api/v1/knowledge/{{knowledge_id}}/embeddings?embeddings=vector_data&vectorIndexId=index_123",
              "host": ["{{base_url}}"],
              "path": ["api", "v1", "knowledge", "{{knowledge_id}}", "embeddings"],
              "query": [
                {"key": "embeddings", "value": "vector_data"},
                {"key": "vectorIndexId", "value": "index_123"}
              ]
            }
          }
        }
      ]
    },
    {
      "name": "Chat & Conversations",
      "item": [
        {
          "name": "Create Conversation",
          "request": {
            "method": "POST",
            "header": [
              {
                "key": "Content-Type",
                "value": "application/json"
              },
              {
                "key": "X-User-Id",
                "value": "{{user_id}}"
              }
            ],
            "body": {
              "mode": "raw",
              "raw": "{\n  \"title\": \"Discussion about AI Research\",\n  \"projectId\": {{project_id}}\n}"
            },
            "url": {
              "raw": "{{base_url}}/api/v1/conversations",
              "host": ["{{base_url}}"],
              "path": ["api", "v1", "conversations"]
            }
          }
        },
        {
          "name": "Get Conversation by ID",
          "request": {
            "method": "GET",
            "header": [
              {
                "key": "X-User-Id",
                "value": "{{user_id}}"
              }
            ],
            "url": {
              "raw": "{{base_url}}/api/v1/conversations/{{conversation_id}}",
              "host": ["{{base_url}}"],
              "path": ["api", "v1", "conversations", "{{conversation_id}}"]
            }
          }
        },
        {
          "name": "List User Conversations",
          "request": {
            "method": "GET",
            "header": [
              {
                "key": "X-User-Id",
                "value": "{{user_id}}"
              }
            ],
            "url": {
              "raw": "{{base_url}}/api/v1/conversations?page=0&size=20",
              "host": ["{{base_url}}"],
              "path": ["api", "v1", "conversations"],
              "query": [
                {"key": "page", "value": "0"},
                {"key": "size", "value": "20"}
              ]
            }
          }
        },
        {
          "name": "Search Conversations",
          "request": {
            "method": "GET",
            "header": [
              {
                "key": "X-User-Id",
                "value": "{{user_id}}"
              }
            ],
            "url": {
              "raw": "{{base_url}}/api/v1/conversations/search?q=AI&page=0&size=20",
              "host": ["{{base_url}}"],
              "path": ["api", "v1", "conversations", "search"],
              "query": [
                {"key": "q", "value": "AI"},
                {"key": "page", "value": "0"},
                {"key": "size", "value": "20"}
              ]
            }
          }
        },
        {
          "name": "Archive Conversation",
          "request": {
            "method": "PUT",
            "header": [
              {
                "key": "X-User-Id",
                "value": "{{user_id}}"
              }
            ],
            "url": {
              "raw": "{{base_url}}/api/v1/conversations/{{conversation_id}}/archive",
              "host": ["{{base_url}}"],
              "path": ["api", "v1", "conversations", "{{conversation_id}}", "archive"]
            }
          }
        },
        {
          "name": "Create Chat Message",
          "request": {
            "method": "POST",
            "header": [
              {
                "key": "Content-Type",
                "value": "application/json"
              },
              {
                "key": "X-User-Id",
                "value": "{{user_id}}"
              }
            ],
            "body": {
              "mode": "raw",
              "raw": "{\n  \"conversationId\": {{conversation_id}},\n  \"content\": \"What are the main findings in the uploaded research papers?\",\n  \"messageType\": \"TEXT\",\n  \"role\": \"USER\"\n}"
            },
            "url": {
              "raw": "{{base_url}}/api/v1/chat-messages",
              "host": ["{{base_url}}"],
              "path": ["api", "v1", "chat-messages"]
            }
          }
        },
        {
          "name": "Get Conversation Messages",
          "request": {
            "method": "GET",
            "header": [
              {
                "key": "X-User-Id",
                "value": "{{user_id}}"
              }
            ],
            "url": {
              "raw": "{{base_url}}/api/v1/chat-messages/conversation/{{conversation_id}}?page=0&size=50",
              "host": ["{{base_url}}"],
              "path": ["api", "v1", "chat-messages", "conversation", "{{conversation_id}}"],
              "query": [
                {"key": "page", "value": "0"},
                {"key": "size", "value": "50"}
              ]
            }
          }
        },
        {
          "name": "Get All Conversation Messages",
          "request": {
            "method": "GET",
            "header": [
              {
                "key": "X-User-Id",
                "value": "{{user_id}}"
              }
            ],
            "url": {
              "raw": "{{base_url}}/api/v1/chat-messages/conversation/{{conversation_id}}/all",
              "host": ["{{base_url}}"],
              "path": ["api", "v1", "chat-messages", "conversation", "{{conversation_id}}", "all"]
            }
          }
        }
      ]
    }
  ],
  "variable": [
    {
      "key": "base_url",
      "value": "http://localhost:8080",
      "type": "string"
    },
    {
      "key": "user_id",
      "value": "1",
      "type": "string"
    },
    {
      "key": "project_id",
      "value": "1",
      "type": "string"
    },
    {
      "key": "document_id",
      "value": "1",
      "type": "string"
    },
    {
      "key": "job_id",
      "value": "job-uuid-here",
      "type": "string"
    },
    {
      "key": "knowledge_id",
      "value": "1",
      "type": "string"
    },
    {
      "key": "conversation_id",
      "value": "1",
      "type": "string"
    },
    {
      "key": "username",
      "value": "john_doe",
      "type": "string"
    }
  ]
}